{
  "project_info": {
    "project_number": "1096043280453",
    "project_id": "kali-studio-app",
    "storage_bucket": "kali-studio-app.firebasestorage.app"
  },
  "client": [
    {
      "client_info": {
        "mobilesdk_app_id": "1:1096043280453:android:023a91adb564c091714b2c",
        "android_client_info": {
          "package_name": "com.argity.turnos"
        }
      },
      "oauth_client": [],
      "api_key": [
        {
          "current_key": "AIzaSyCItmkOEWG6KPwTMeu3YHunrYucSUW0iC8"
        }
      ],
      "services": {
        "appinvite_service": {
          "other_platform_oauth_client": []
        }
      }
    }
  ],
  "configuration_version": "1"
}